gemma_mcp/__init__.py
gemma_mcp/gemma_client.py
gemma_mcp-0.1.1.dist-info/METADATA
gemma_mcp-0.1.1.dist-info/WHEEL
gemma_mcp-0.1.1.dist-info/top_level.txt
gemma_mcp-0.1.1.dist-info/RECORD
