Metadata-Version: 2.4
Name: gemma-mcp
Version: 0.1.1
Summary: MCP client and function calling for Gemma-3
Author-email: Yusuf Sarıgöz <yusufsarigoz@gmail.com>
Project-URL: homepage, https://github.com/monatis/gemma-mcp
Project-URL: project, https://github.com/monatis/gemma-mcp
Project-URL: repository, https://github.com/monatis/gemma-mcp
Keywords: gemma,gemma3,mcp,function-calling
Classifier: Intended Audience :: Developers
Classifier: License :: OSI Approved :: MIT License
Classifier: Programming Language :: Python :: 3.10
Classifier: Programming Language :: Python :: 3.11
Classifier: Programming Language :: Python :: 3.12
Classifier: Topic :: Software Development :: Libraries :: Python Modules
Requires-Python: >=3.10
Requires-Dist: google-genai
Requires-Dist: fastmcp
Provides-Extra: dev
Requires-Dist: pytest>=8.3.4; extra == "dev"
